odoo/addons/product_usability/README.rst
odoo/addons/product_usability/__init__.py
odoo/addons/product_usability/__manifest__.py
odoo/addons/product_usability/i18n/fr.po
odoo/addons/product_usability/i18n/it.po
odoo/addons/product_usability/i18n/product_usability.pot
odoo/addons/product_usability/readme/CONTRIBUTORS.md
odoo/addons/product_usability/readme/DESCRIPTION.md
odoo/addons/product_usability/readme/ROADMAP.md
odoo/addons/product_usability/security/ir.model.access.csv
odoo/addons/product_usability/security/res_groups.xml
odoo/addons/product_usability/static/description/icon.png
odoo/addons/product_usability/static/description/index.html
odoo/addons/product_usability/static/description/main_menu.png
odoo/addons/product_usability/static/description/product_menu_icon.png
odoo/addons/product_usability/static/description/product_menu_icon.svg
odoo/addons/product_usability/views/menu.xml
odoo_addon_product_usability-17.0.1.0.0.2.dist-info/METADATA
odoo_addon_product_usability-17.0.1.0.0.2.dist-info/WHEEL
odoo_addon_product_usability-17.0.1.0.0.2.dist-info/top_level.txt
odoo_addon_product_usability-17.0.1.0.0.2.dist-info/RECORD
